bitget_python_connector/__init__.py
bitget_python_connector/client.py
bitget_python_connector/consts.py
bitget_python_connector/exceptions.py
bitget_python_connector/utils.py
bitget_python_connector/broker/account_api.py
bitget_python_connector/broker/manage_api.py
bitget_python_connector/mix/__init__.py
bitget_python_connector/mix/account_api.py
bitget_python_connector/mix/market_api.py
bitget_python_connector/mix/order_api.py
bitget_python_connector/mix/plan_api.py
bitget_python_connector/mix/position_api.py
bitget_python_connector/mix/trace_api.py
bitget_python_connector/spot/__init__.py
bitget_python_connector/spot/account_api.py
bitget_python_connector/spot/market_api.py
bitget_python_connector/spot/order_api.py
bitget_python_connector/spot/plan_api.py
bitget_python_connector/spot/public_api.py
bitget_python_connector/spot/wallet_api.py
bitget_python_connector/ws/bitget_ws_client.py
bitget_python_connector/ws/utils/sign_utils.py
examples/mix_example.py
examples/spot_example.py
examples/websocket.py
bitget_python_connector-0.0.7.dist-info/LICENSE
bitget_python_connector-0.0.7.dist-info/METADATA
bitget_python_connector-0.0.7.dist-info/WHEEL
bitget_python_connector-0.0.7.dist-info/top_level.txt
bitget_python_connector-0.0.7.dist-info/RECORD
