Metadata-Version: 2.1
Name: bitget-python-connector
Version: 0.0.7
Summary: A tool to easily connect to bitget api.
Author-email: "Cheng, Chuan-Yi" <parker178912.en08@nycu.edu.tw>
Project-URL: Homepage, https://github.com/parker178912/bitget-python-connector
Project-URL: Bug Tracker, https://github.com/parker178912/bitget-python-connector/issues
Classifier: Programming Language :: Python :: 3
Classifier: License :: OSI Approved :: MIT License
Classifier: Operating System :: OS Independent
Requires-Python: >=3.7
License-File: LICENSE
Requires-Dist: requests
